agent_adapters/__init__.py
agent_adapters/anthropic_adapter.py
agent_adapters/base.py
agent_adapters/openai_adapter.py
corefoundry/__init__.py
corefoundry/agent.py
corefoundry/core.py
corefoundry-0.3.0.dist-info/licenses/LICENSE
corefoundry-0.3.0.dist-info/METADATA
corefoundry-0.3.0.dist-info/WHEEL
corefoundry-0.3.0.dist-info/top_level.txt
corefoundry-0.3.0.dist-info/RECORD
