Metadata-Version: 2.4
Name: corefoundry
Version: 0.3.0
Summary: A lightweight, LLM-agnostic micro-framework for AI agent tool management.
Author: jjhiza
License: MIT
Project-URL: Homepage, https://github.com/jjhiza/core-foundry
Project-URL: Repository, https://github.com/jjhiza/core-foundry
Project-URL: Issues, https://github.com/jjhiza/core-foundry/issues
Project-URL: Documentation, https://github.com/jjhiza/core-foundry#readme
Keywords: ai,agents,llm,tools,openai,anthropic,framework
Classifier: Development Status :: 4 - Beta
Classifier: Intended Audience :: Developers
Classifier: License :: OSI Approved :: MIT License
Classifier: Programming Language :: Python :: 3
Classifier: Programming Language :: Python :: 3.9
Classifier: Programming Language :: Python :: 3.10
Classifier: Programming Language :: Python :: 3.11
Classifier: Programming Language :: Python :: 3.12
Classifier: Topic :: Software Development :: Libraries :: Python Modules
Classifier: Topic :: Scientific/Engineering :: Artificial Intelligence
Requires-Python: >=3.9
License-File: LICENSE
Requires-Dist: pydantic>=2.0
Provides-Extra: adapters
Requires-Dist: openai>=1.0.0; extra == "adapters"
Requires-Dist: anthropic>=0.18.0; extra == "adapters"
Dynamic: license-file
